nba_api/__init__.py
nba_api/library/__init__.py
nba_api/library/_enum_base.py
nba_api/library/debug/__init__.py
nba_api/library/debug/debug.py
nba_api/library/http.py
nba_api/live/__init__.py
nba_api/live/nba/__init__.py
nba_api/live/nba/endpoints/__init__.py
nba_api/live/nba/endpoints/_base.py
nba_api/live/nba/endpoints/boxscore.py
nba_api/live/nba/endpoints/odds.py
nba_api/live/nba/endpoints/playbyplay.py
nba_api/live/nba/endpoints/scoreboard.py
nba_api/live/nba/library/__init__.py
nba_api/live/nba/library/http.py
nba_api/stats/__init__.py
nba_api/stats/endpoints/__init__.py
nba_api/stats/endpoints/_base.py
nba_api/stats/endpoints/_expected_data/__init__.py
nba_api/stats/endpoints/_expected_data/boxscoresummaryv3.py
nba_api/stats/endpoints/_expected_data/dunkscoreleaders.py
nba_api/stats/endpoints/_expected_data/scoreboardv3.py
nba_api/stats/endpoints/_parsers/__init__.py
nba_api/stats/endpoints/_parsers/boxscoreadvancedv3.py
nba_api/stats/endpoints/_parsers/boxscoredefensivev2.py
nba_api/stats/endpoints/_parsers/boxscorefourfactorsv3.py
nba_api/stats/endpoints/_parsers/boxscorehustlev2.py
nba_api/stats/endpoints/_parsers/boxscorematchupsv3.py
nba_api/stats/endpoints/_parsers/boxscoremiscv3.py
nba_api/stats/endpoints/_parsers/boxscoreplayertrackv3.py
nba_api/stats/endpoints/_parsers/boxscorescoringv3.py
nba_api/stats/endpoints/_parsers/boxscoresummaryv3.py
nba_api/stats/endpoints/_parsers/boxscoretraditionalv3.py
nba_api/stats/endpoints/_parsers/boxscoreusagev3.py
nba_api/stats/endpoints/_parsers/iststandings.py
nba_api/stats/endpoints/_parsers/playbyplayv3.py
nba_api/stats/endpoints/_parsers/scheduleleaguev2.py
nba_api/stats/endpoints/_parsers/scoreboardv3.py
nba_api/stats/endpoints/alltimeleadersgrids.py
nba_api/stats/endpoints/assistleaders.py
nba_api/stats/endpoints/assisttracker.py
nba_api/stats/endpoints/boxscoreadvancedv2.py
nba_api/stats/endpoints/boxscoreadvancedv3.py
nba_api/stats/endpoints/boxscoredefensivev2.py
nba_api-1.11.2.dist-info/METADATA
nba_api-1.11.2.dist-info/WHEEL
nba_api-1.11.2.dist-info/licenses/LICENSE
nba_api-1.11.2.dist-info/RECORD
