Metadata-Version: 2.4
Name: nba_api
Version: 1.11.2
Summary: An API Client package to access the APIs for NBA.com
License-Expression: MIT
License-File: LICENSE
Keywords: api,basketball,data,nba,sports,stats
Author: Swar Patel
Author-email: <swar.m.patel@gmail.com>
Maintainer: Swar Patel
Maintainer-email: <swar.m.patel@gmail.com>
Requires-Python: >=3.10
Classifier: Intended Audience :: Developers
Classifier: Intended Audience :: Science/Research
Classifier: License :: OSI Approved :: MIT License
Classifier: Operating System :: OS Independent
Classifier: Topic :: Software Development
Classifier: Programming Language :: Python
Classifier: Programming Language :: Python :: 3
Classifier: Programming Language :: Python :: 3 :: Only
Classifier: Programming Language :: Python :: 3.10
Classifier: Programming Language :: Python :: 3.11
Classifier: Programming Language :: Python :: 3.12
Classifier: Programming Language :: Python :: 3.13
Requires-Dist: numpy (>=1.26.0) ; python_version < "3.13"
Requires-Dist: numpy (>=2.1.0) ; python_version >= "3.13"
Requires-Dist: pandas (>=2.1.0) ; python_version < "3.12"
Requires-Dist: pandas (>=2.2.0) ; python_version >= "3.12"
Requires-Dist: requests (>=2.32.3,<3.0.0)
Project-URL: Bug Tracker, https://github.com/swar/nba_api/issues
Project-URL: Documentation, https://github.com/swar/nba_api/blob/master/README.md
Project-URL: Repository, https://github.com/swar/nba_api
